coref/__init__.py
coref/app.py
coref/arrghs.py
coref/cfg.py
coref/gevent.py
coref/help.py
coref/hylang.py
coref/init.py
coref/mod.py
coref/ns.py
coref/version.py
coref/internal/__init__.py
coref/internal/dp.py
coref/internal/path.py
coref/internal/rb.py
coref/internal/util.py
coref/internal/v.py
coref/internal/monad/Dict.py
coref/internal/monad/L.py
coref/internal/monad/Namespace.py
coref/internal/monad/Tpl.py
coref/internal/monad/__init__.py
coref/internal/monad/internal.py
coref/stdlib/__init__.py
coref/stdlib/cmd/__init__.py
coref/stdlib/cmd/about.py
coref/stdlib/cmd/banner.py
coref/stdlib/cmd/license.py
coref/stdlib/cmd/loop.py
coref/stdlib/cmd/status.py
coref/stdlib/f/__init__.py
coref/stdlib/f/f.py
coref/stdlib/f/gevent.py
coref/stdlib/f/init.py
coref/stdlib/f/time.py
coref/stdlib/filesystem/__init__.py
coref/stdlib/filesystem/arrghs.py
coref/stdlib/filesystem/base.py
coref/stdlib/filesystem/cfg.py
coref/stdlib/filesystem/console.py
coref/stdlib/filesystem/env.py
coref/stdlib/filesystem/env_local.py
coref/stdlib/filesystem/env_variables.py
coref/stdlib/filesystem/help.py
coref/stdlib/filesystem/tb.py
coref/stdlib/filesystem/version.py
coref/stdlib/sys/__init__.py
coref/stdlib/sys/cfg.py
coref/stdlib/sys/gevent.py
coref/stdlib/sys/hylang.py
coref/stdlib/sys/init.py
coref-0.0.3.dist-info/LICENSE
coref-0.0.3.dist-info/METADATA
coref-0.0.3.dist-info/WHEEL
coref-0.0.3.dist-info/top_level.txt
coref-0.0.3.dist-info/RECORD
