Metadata-Version: 2.1
Name: coref
Version: 0.0.3
Summary: Functional, Namespace-based application CORE
Home-page: https://github.com/vulogov/coref
Author: Vladimir Ulogov
Author-email: vladimir.ulogov@me.com
License: GPL3
Platform: UNKNOWN
Classifier: Programming Language :: Python :: 3
Classifier: Development Status :: 3 - Alpha
Classifier: Intended Audience :: Information Technology
Classifier: License :: OSI Approved :: GNU General Public License v3 (GPLv3)
Classifier: Operating System :: OS Independent
Classifier: Topic :: Software Development :: Libraries
Classifier: Topic :: Software Development :: Libraries :: Application Frameworks
Requires-Python: >=3.6
Requires-Dist: appdirs (==1.4.4)
Requires-Dist: appnope (==0.1.0)
Requires-Dist: APScheduler (==3.6.3)
Requires-Dist: args (==0.1.0)
Requires-Dist: Arpeggio (==1.9.2)
Requires-Dist: astor (==0.8.1)
Requires-Dist: attrs (==19.3.0)
Requires-Dist: backcall (==0.1.0)
Requires-Dist: bleach (==3.1.5)
Requires-Dist: certifi (==2020.4.5.1)
Requires-Dist: cffi (==1.14.0)
Requires-Dist: chardet (==3.0.4)
Requires-Dist: Cheetah3 (==3.2.5)
Requires-Dist: Click (==7.0)
Requires-Dist: clint (==0.5.1)
Requires-Dist: colorama (==0.4.3)
Requires-Dist: commonmark (==0.9.1)
Requires-Dist: consolemd (==0.5.1)
Requires-Dist: cryptography (==2.9.2)
Requires-Dist: Cython (==0.29.19)
Requires-Dist: decorator (==4.4.2)
Requires-Dist: dill (==0.3.1.1)
Requires-Dist: docutils (==0.16)
Requires-Dist: fs (==2.4.11)
Requires-Dist: funcparserlib (==0.3.6)
Requires-Dist: gevent (==20.5.0)
Requires-Dist: greenlet (==0.4.15)
Requires-Dist: hy (==0.18.0)
Requires-Dist: idna (==2.9)
Requires-Dist: importlib-metadata (==1.6.0)
Requires-Dist: ipython-genutils (==0.2.0)
Requires-Dist: jedi (==0.17.0)
Requires-Dist: keyring (==21.2.1)
Requires-Dist: lockfile (==0.12.2)
Requires-Dist: more-itertools (==8.3.0)
Requires-Dist: mypy-lang (==0.5.0)
Requires-Dist: networkx (==2.4)
Requires-Dist: numpy (==1.18.4)
Requires-Dist: numpy-ringbuffer (==0.2.1)
Requires-Dist: OSlash (==0.5.1)
Requires-Dist: packaging (==20.3)
Requires-Dist: parso (==0.7.0)
Requires-Dist: pathlib (==1.0.1)
Requires-Dist: pexpect (==4.8.0)
Requires-Dist: pickleshare (==0.7.5)
Requires-Dist: pkginfo (==1.5.0.1)
Requires-Dist: pluggy (==0.13.1)
Requires-Dist: prompt-toolkit (==3.0.5)
Requires-Dist: psutil (==5.7.0)
Requires-Dist: ptyprocess (==0.6.0)
Requires-Dist: py (==1.8.1)
Requires-Dist: pycparser (==2.20)
Requires-Dist: pyfiglet (==0.8.post1)
Requires-Dist: Pygments (==2.6.1)
Requires-Dist: pyparsing (==2.4.7)
Requires-Dist: pytest (==5.4.2)
Requires-Dist: pytz (==2020.1)
Requires-Dist: PyYAML (==5.3.1)
Requires-Dist: pyzmq (==19.0.1)
Requires-Dist: readme-renderer (==26.0)
Requires-Dist: requests (==2.23.0)
Requires-Dist: requests-toolbelt (==0.9.1)
Requires-Dist: rfc3986 (==1.4.0)
Requires-Dist: rply (==0.7.7)
Requires-Dist: setproctitle (==1.1.10)
Requires-Dist: six (==1.14.0)
Requires-Dist: texttable (==1.6.2)
Requires-Dist: textX (==2.1.0)
Requires-Dist: tqdm (==4.46.1)
Requires-Dist: traitlets (==4.3.3)
Requires-Dist: twine (==3.2.0)
Requires-Dist: tzlocal (==2.1)
Requires-Dist: urllib3 (==1.25.9)
Requires-Dist: vedis (==0.7.1)
Requires-Dist: wcwidth (==0.1.9)
Requires-Dist: webencodings (==0.5.1)
Requires-Dist: zipp (==3.1.0)
Requires-Dist: zmq (==0.0.0)
